Physical2FA/__init__.py
Physical2FA/decrypt.py
Physical2FA/encrypt.py
Physical2FA/write_key.py
Physical2FA-1.1.0.dist-info/LICENSE
Physical2FA-1.1.0.dist-info/METADATA
Physical2FA-1.1.0.dist-info/WHEEL
Physical2FA-1.1.0.dist-info/top_level.txt
Physical2FA-1.1.0.dist-info/RECORD
