Metadata-Version: 2.1
Name: Physical2FA
Version: 1.1.0
Summary: Encryption using 2 Factor Authentication through an external drive.
Home-page: https://github.com/Atharv2/Physical2FA
Author: Atharv2
Author-email: atharv260107@gmail.com
License: UNKNOWN
Platform: UNKNOWN
Classifier: Programming Language :: Python :: 3
Classifier: License :: OSI Approved :: GNU Lesser General Public License v3 (LGPLv3)
Classifier: Operating System :: OS Independent
Classifier: Development Status :: 5 - Production/Stable
Classifier: Environment :: Win32 (MS Windows)
Classifier: Operating System :: Microsoft :: Windows :: Windows 7
Classifier: Operating System :: Microsoft :: Windows :: Windows 8
Classifier: Operating System :: Microsoft :: Windows :: Windows 8.1
Classifier: Operating System :: Microsoft :: Windows :: Windows 10
Classifier: Topic :: Security :: Cryptography
Classifier: Topic :: Security
Requires-Python: >=3.0
